neuralnet_pytorch/__init__.py
neuralnet_pytorch/_version.py
neuralnet_pytorch/layers.py
neuralnet_pytorch/metrics.py
neuralnet_pytorch/monitor.py
neuralnet_pytorch/normalization.py
neuralnet_pytorch/optimizer.py
neuralnet_pytorch/resizing.py
neuralnet_pytorch/test.py
neuralnet_pytorch/utils.py
neuralnet_pytorch-0.0.3.dist-info/LICENSE.txt
neuralnet_pytorch-0.0.3.dist-info/METADATA
neuralnet_pytorch-0.0.3.dist-info/WHEEL
neuralnet_pytorch-0.0.3.dist-info/top_level.txt
neuralnet_pytorch-0.0.3.dist-info/RECORD
