Metadata-Version: 2.1
Name: neuralnet-pytorch
Version: 0.0.3
Summary: A high-level library on top of Pytorch.
Home-page: https://github.com/justanhduc/neuralnet-pytorch
Author: Duc Nguyen
Author-email: adnguyen@yonsei.ac.kr
License: UNKNOWN
Project-URL: Bug Reports, https://github.com/justanhduc/neuralnet-pytorch/issues
Project-URL: Source, https://github.com/justanhduc/neuralnet-pytorch
Platform: Windows
Platform: Linux
Classifier: Development Status :: 3 - Alpha
Classifier: Intended Audience :: End Users/Desktop
Classifier: License :: OSI Approved :: Mozilla Public License 2.0 (MPL 2.0)
Classifier: Operating System :: Microsoft :: Windows :: Windows 10
Classifier: Operating System :: POSIX :: Linux
Classifier: Programming Language :: Python :: 3 :: Only
Classifier: Programming Language :: Python :: 3.5
Requires-Dist: visdom
Requires-Dist: matplotlib
Requires-Dist: scipy
Requires-Dist: numpy
